{
  "lastUpdated": "2026-05-19T18:22:29.816Z",
  "officialPosts": [
    {
      "title": "클라이언트 1.2.415 업데이트 안내",
      "date": "2026년 5월 14일",
      "content": "",
      "link": "https://maplestory.nexon.com/news/update/804",
      "isRecent": false
    },
    {
      "title": "클라이언트 1.2.414(3) 업데이트 안내",
      "date": "",
      "content": "",
      "link": "https://maplestory.nexon.com/news/update/803",
      "isRecent": false
    },
    {
      "title": "수정 클라이언트 1.2.414 업데이트 안내 (이벤트, 컨텐츠, 개선사항 및 오류 수정)",
      "date": "2026년 4월 17일",
      "content": "",
      "link": "https://maplestory.nexon.com/news/update/802",
      "isRecent": false
    },
    {
      "title": "수정 클라이언트 1.2.414 업데이트 안내 (공용 코어, 스킬 조정)",
      "date": "2026년 4월 20일",
      "content": "",
      "link": "https://maplestory.nexon.com/news/update/801",
      "isRecent": false
    },
    {
      "title": "클라이언트 1.2.413(4) 업데이트 안내",
      "date": "",
      "content": "",
      "link": "https://maplestory.nexon.com/news/update/800",
      "isRecent": false
    }
  ],
  "dcPosts": [
    {
      "title": "낭만의시대에는 은꼴갤이라는게있었는데..",
      "content": "거기에막교복입은여자사진 ㅈㄴ올라오고.. 성능고려x 오로지 고점컨기준 난이도순위S 에반 카데나A 제로B 칼리 불독C 메르 아크 블래D 데벤E 카인 섀도어 스커이외 나머지는 개딸깍직업컨트롤직업중 유일하게 말이안되는리턴가진 에반살려내라"
    },
    {
      "title": "귾대 저 영상만 보면 연버가 먼저 시비건줄알듯,,",
      "content": "표창은 걍 이 글보고 긁혀서 쌍욕박은건대 ㄹㅇ,,"
    },
    {
      "title": "아니 마지막글이 지기분이 상한다는게 이게 맞냐",
      "content": "그딴거 아무도 안궁금하다니까아니 왜 시선을 지한테 끌려고하는거지 미띠겠네"
    },
    {
      "title": "와씨발 진짜찾았다 ㅋㅋㅋㅋㅋㅋㅋㅋㅋㅋㅋㅋ",
      "content": "2렙에 피150탈리야 찾았다 ㅋㅋㅋㅋㅋㅋㅋㅋㅋㅋ"
    },
    {
      "title": "아 진혁아 미안하다 고소 안당했구나",
      "content": "미안하다게이야ㅋㅋㅋㅋㅋ"
    },
    {
      "title": "와 교복은 ai알바가 걍 5초삭해버리나보네",
      "content": "난봤다 성능고려x 오로지 고점컨기준 난이도순위S 에반 카데나A 제로B 칼리 불독C 메르 아크 블래D 데벤E 카인 섀도어 스커이외 나머지는 개딸깍직업컨트롤직업중 유일하게 말이안되는리턴가진 에반살려내라"
    },
    {
      "title": "모도 라인업 꼬라지 시발 ㅋㅋㅋㅋ",
      "content": "박진혁 염방원 표창 이쿠(뒷담) ㅋㅋㅋㅋㅋㅋㅋ"
    },
    {
      "title": "인벤 인생망한놈< 솔직히 좆병신같으면 개추",
      "content": "대놓고 말하던가 무슨 뇌성마비 장애인같음 병신새기"
    },
    {
      "title": "찾았다!",
      "content": "젠지월즈무관범인 - dc official App"
    },
    {
      "title": "메벤 별거 없노 ㅋㅋㅋ 혐오글 쏴주면 십추가노",
      "content": "박진혁"
    },
    {
      "title": "나도 후닝한테 고소장 온거 인증해봄",
      "content": "순정༺✣༻꧁꙳͉̀⛧༒⛧꙳͉̀꧂༺✣༻​"
    },
    {
      "title": "사실여기서 연버쌤이 후쌤 긁은글 인벤에올려야 허니잼인데..",
      "content": "그게진짜 존나재밌는글이었는데 하.. 성능고려x 오로지 고점컨기준 난이도순위S 에반 카데나A 제로B 칼리 불독C 메르 아크 블래D 데벤E 카인 섀도어 스커이외 나머지는 개딸깍직업컨트롤직업중 유일하게 말이안되는리턴가진 에반살려내라"
    },
    {
      "title": "그니까 정리하자면 이거임?",
      "content": "연버= 시비 먼저 걸었음 나로후닝 캡틴 못한다고 깜 나로후닝=그거 우연히보고 욕함 이거잖아 그럼 연버도 잘못있는거아님? 아니 단순히 쿨뚝 지적했다고 나로후닝이 저정도까지욕한다고??"
    },
    {
      "title": "아시아 역대 베스트 11 이면 월드컵 어디까지 가능?",
      "content": "각 선수 전부 최전성기 나이랑 폼으로 데려오고 나머지 팀들은 전부 그 당시 한 세대 베스트로만 나오고 2002~2022 중 하나 랜덤으로 참여한다고 치면 - dc official App"
    },
    {
      "title": "보지에 얼음 넣고 녹이고 싶은 여갤러 고닉 목록.txt",
      "content": "썽코오리 = 율곰탱 주현쟝 공진아 둘기콘 보라색외가리 메갤용고닉 설무디 itistoa (소라) 토아 반고닉 하얀밥위에후라이 ㅁㅋㅂㅁ seek4606(작약°) 시크 누나 ㅇㅇ(buldakbibim) 불닥비빔 반고닉 ㅇㅇ(o7mz3gqe4hyb) 쭐어 반고닉 함사랑 소나기 쿠션 ㅅㅁ OwlHolic(안녕부엉아) 잉잉잠와 혜수혜수 씹커여움 왕찌찌 베지밀B 베지밀Ｂ 딸기 히히 미르와함께춤을 (ㄸㅇㅉ남편) (?) ㅁㅇ ㆄㅅㆄ 포코리 돈통 림잉 하은쟝 444 224 세로켈 쯔위안 쿠커넴 린드 갈비 종려 rice 뿧 일이삼사나 텐노지리나 히므 은시계 부적 하와와와왕 메부이 겜돌 코력 안나쟝 유미 끼잉 달체 꼬맹 메딱 슈꾸림 삼중하나 흐빵(runny0035) 새부 웃기는짬뽕 \"캐릭터2배\" 끼티 까메. 밤되님 메갤용고닉1 = ㄹㄹㅇ 스햐사랑단 = 말랑찹쌀톡기 꺄프틴 줄섬 려네 으응 슨퀴 Arapi 나예 예닮 행복한뀽뀽이 주디 모여 게질알 ㅇㅇ(aimyon123) bero55 bero 섹파 ㅂㅇ 눌이 연필 리테 도넛 우메다 호두조아 Jend 원희 아이 타천사 꼬젬죠 꼬맹 앙녕 ㅇㅇ(dovmfdl) 메갤러(58.126) 버섯이 성냥파리 로미、 ㅇㅇ(brake3550) 부라케 반고닉 슬퍼 아님 힉힉꼬물이 s e x 서찢(존예지) 피버 치민 애정 싫음 수밍 똑단발 별소리 만두좋아해? Celest 초서 ㅇㅇ(pioneer1090) 133.32 ㅇㅇ(penny2705) 부엉ㅇ 륵미 토빵 쥬~지 쥬땜무 찐빵 재재 히히니 ㄸㅇㅉ 빠코(인게임 닉 루비) ㅇㅇ(light2734) 은아 누나 ㅇㅇ(dpfwnaak) 엘 누나 세레나 윈브(서하율)"
    },
    {
      "title": "'카리나' 데뷔 전 영상 유출",
      "content": "http://tiktok.com/9Dx2AdMmIpd현재 틱톡에 영상 박제된 상태ㄷㄷc9"
    }
  ],
  "invenPosts": [
    {
      "title": "루시드 버닝 히든미션 2개 / 5월 패치로 바뀌는 것들/메할일/보상 요약+@",
      "content": "[수정/추가 사항]1. 메할일 부분의 메이플포인트샵 기간 오타 수정 2. 본섭 오면서 추가된 루시드 버닝 히든 미션3. 윷놀이 기간 수정 : ~5/27(수) -----------------------------------------------------* 참여 조건 : 루시드 레벨 80 이상1) 체인지 버닝 수락한 캐릭터로 석촌호수 루시드에게 말 걸기 -> 노틸러스 침실 입장 -> 꿈의 미로 클리어 :- 체인지 버닝 : 루시드 이펙트 ▶ 꿈의 미로 관련 사항 : 재시도가 불가능해서 제가 클리어한 기준으로 적었습니다. 이 때문에 혹시 거쳐야 하는 맵 수의 경우는 이와 차이가 있을 수 있습니다- 1번째 맵 입장 시 나비들이 줄지어서 가리키는 포탈로 입장- 2번째, 3번째 맵에서는 머리 중앙에 더듬이가 있는 나비의 옆 포탈로 입장 -> 클리어* 예시 - 왼쪽 : 더듬이 있음 / 오른쪽 : 더듬이 없음 2) 이펙트 착용하고 석촌호수 루시드와 대화 - 루시드의 드림캐처 : 메이플 홈 가구 * 위의 아이템 이미지들은 섣버 님 블로그 출처입니다 : https://blog.naver.com/seotbeo/224284910222** 맨 처음 발견하신 분 글 링크 : https://www.inven.co.kr/board/maple/5974/6570585-----------------------------안녕하세요 이 글은 5/14(목) 진행되는 업데이트의 중요한 내용들을 각 테마별로 빠르게 확인하실 수 있게 한 글입니다 잘못 적혔거나 누락된 부분 발견 시 말씀해 주시면 감사히 수정하겠습니다 [목차]1. 5/13(수) 23:59"
    },
    {
      "title": "이제 카르마 안 풀고 대적자만 풀 확률도 있음?",
      "content": "창섭이햄이 전승권 내면서 재설정처럼 메소 써서 하는거 가치 올려서 유의미 하게 만들겠다 했는데 그러면 앞으로 카르마 블화에 없이 보스 코인샵 같은 곳에서 대적자만 많이 풀 확률도 있나? noKidnap('imageCollectDiv'); INVEN.Media.Resizer.collect('imageCollectDiv', '740'); // 신고하기 function report_bd() { var params = \"\"; params = \"rcidx=3&comeidx=5974&uid=6587670\"; INVEN.Links.reportArticle(params); } // 광고신고 INVEN.Links.spamArticle = function(params) { var repWin = window.open(\"https://www.inven.co.kr/common/report/spam/?\" + params,\"\",\"left=100,top=100,width=596,height=480,resizable=no,scrollbars=no,toolbar=0\"); } function report_spam() { var params = \"\"; params = \"type=board&index1=5974&index2=6587670\"; INVEN.Links.spamArticle(params); } // 스크랩 function scrapOpen() { var scrapWin = window.open('about:blank', 'scrap_add', 'left=50,top=50,height=50,width=50,scrollbars=no,res"
    },
    {
      "title": "시발 드디어 노딱 달았다",
      "content": "씹!! noKidnap('imageCollectDiv'); INVEN.Media.Resizer.collect('imageCollectDiv', '740'); // 신고하기 function report_bd() { var params = \"\"; params = \"rcidx=3&comeidx=5974&uid=6587669\"; INVEN.Links.reportArticle(params); } // 광고신고 INVEN.Links.spamArticle = function(params) { var repWin = window.open(\"https://www.inven.co.kr/common/report/spam/?\" + params,\"\",\"left=100,top=100,width=596,height=480,resizable=no,scrollbars=no,toolbar=0\"); } function report_spam() { var params = \"\"; params = \"type=board&index1=5974&index2=6587669\"; INVEN.Links.spamArticle(params); } // 스크랩 function scrapOpen() { var scrapWin = window.open('about:blank', 'scrap_add', 'left=50,top=50,height=50,width=50,scrollbars=no,resizable=no'); var fm = document.getElementById(\"fmAddToScrap\"); fm.target = \"scrap_add\"; fm.submit();"
    },
    {
      "title": "그 연버라는 사람이 쓴 쿨뚝글은 어딨나요",
      "content": "그게 젤 중요해보이는데 안보임... noKidnap('imageCollectDiv'); INVEN.Media.Resizer.collect('imageCollectDiv', '740'); // 신고하기 function report_bd() { var params = \"\"; params = \"rcidx=3&comeidx=5974&uid=6587668\"; INVEN.Links.reportArticle(params); } // 광고신고 INVEN.Links.spamArticle = function(params) { var repWin = window.open(\"https://www.inven.co.kr/common/report/spam/?\" + params,\"\",\"left=100,top=100,width=596,height=480,resizable=no,scrollbars=no,toolbar=0\"); } function report_spam() { var params = \"\"; params = \"type=board&index1=5974&index2=6587668\"; INVEN.Links.spamArticle(params); } // 스크랩 function scrapOpen() { var scrapWin = window.open('about:blank', 'scrap_add', 'left=50,top=50,height=50,width=50,scrollbars=no,resizable=no'); var fm = document.getElementById(\"fmAddToScrap\"); fm.target = \"scrap_ad"
    },
    {
      "title": "와헌 진지하게 어떰?",
      "content": "체급이랑 조작난이도가 제일중요한데 둘 다 어때?렌급으로 쉽나? 체급은 중간정도만되도 되긴함 noKidnap('imageCollectDiv'); INVEN.Media.Resizer.collect('imageCollectDiv', '740'); // 신고하기 function report_bd() { var params = \"\"; params = \"rcidx=3&comeidx=5974&uid=6587667\"; INVEN.Links.reportArticle(params); } // 광고신고 INVEN.Links.spamArticle = function(params) { var repWin = window.open(\"https://www.inven.co.kr/common/report/spam/?\" + params,\"\",\"left=100,top=100,width=596,height=480,resizable=no,scrollbars=no,toolbar=0\"); } function report_spam() { var params = \"\"; params = \"type=board&index1=5974&index2=6587667\"; INVEN.Links.spamArticle(params); } // 스크랩 function scrapOpen() { var scrapWin = window.open('about:blank', 'scrap_add', 'left=50,top=50,height=50,width=50,scrollbars=no,resizable=no'); var fm = document.getElementById(\"fmAddT"
    },
    {
      "title": "방어구 15퍼작",
      "content": "선데이없는 기준 28만~29만이던데선데이하면 절반 생각하면 되지? noKidnap('imageCollectDiv'); INVEN.Media.Resizer.collect('imageCollectDiv', '740'); // 신고하기 function report_bd() { var params = \"\"; params = \"rcidx=3&comeidx=5974&uid=6587666\"; INVEN.Links.reportArticle(params); } // 광고신고 INVEN.Links.spamArticle = function(params) { var repWin = window.open(\"https://www.inven.co.kr/common/report/spam/?\" + params,\"\",\"left=100,top=100,width=596,height=480,resizable=no,scrollbars=no,toolbar=0\"); } function report_spam() { var params = \"\"; params = \"type=board&index1=5974&index2=6587666\"; INVEN.Links.spamArticle(params); } // 스크랩 function scrapOpen() { var scrapWin = window.open('about:blank', 'scrap_add', 'left=50,top=50,height=50,width=50,scrollbars=no,resizable=no'); var fm = document.getElementById(\"fmAddToScrap\"); fm.t"
    },
    {
      "title": "챌섭 아란 vs 썬콜 추천좀!!!",
      "content": "여태 전사만 두캐릭(렌, 닼나) 해방했는데 이번 챌섭 때썬콜 vs 아란 뭐가 ㄱㅊ을까?아란이 사냥은 안좋아도 프리드 개편돼서 나중에 주보돌기 편하고썬콜은 챌섭에선 많이 힘들지만 본섭가서 투자하면 좋아진다고 들어서 고민이야… 본섭도 아직 이칼까지만 가서 많이 약해ㅠ둘 중에 뭘 더 추천해?! noKidnap('imageCollectDiv'); INVEN.Media.Resizer.collect('imageCollectDiv', '740'); // 신고하기 function report_bd() { var params = \"\"; params = \"rcidx=3&comeidx=5974&uid=6587665\"; INVEN.Links.reportArticle(params); } // 광고신고 INVEN.Links.spamArticle = function(params) { var repWin = window.open(\"https://www.inven.co.kr/common/report/spam/?\" + params,\"\",\"left=100,top=100,width=596,height=480,resizable=no,scrollbars=no,toolbar=0\"); } function report_spam() { var params = \"\"; params = \"type=board&index1=5974&index2=6587665\"; INVEN.Links.spamArticle(params); } // 스크랩 function scrapOpen() { var scrapWin = window.open('about:blank', 'scrap_"
    },
    {
      "title": "유챔템값 정상화된듯",
      "content": "옛날엔 이정도면 70억은 받았을건데 각각 44억 55억에 가져옴둘다 17성이고 추옵, 에디 되있는거 호감이라 바로 삼작이야 다시 치면되고 noKidnap('imageCollectDiv'); INVEN.Media.Resizer.collect('imageCollectDiv', '740'); // 신고하기 function report_bd() { var params = \"\"; params = \"rcidx=3&comeidx=5974&uid=6587664\"; INVEN.Links.reportArticle(params); } // 광고신고 INVEN.Links.spamArticle = function(params) { var repWin = window.open(\"https://www.inven.co.kr/common/report/spam/?\" + params,\"\",\"left=100,top=100,width=596,height=480,resizable=no,scrollbars=no,toolbar=0\"); } function report_spam() { var params = \"\"; params = \"type=board&index1=5974&index2=6587664\"; INVEN.Links.spamArticle(params); } // 스크랩 function scrapOpen() { var scrapWin = window.open('about:blank', 'scrap_add', 'left=50,top=50,height=50,width=50,scrollbars=no,resizable=no'); var fm = docum"
    },
    {
      "title": "에테르넬 3세트 깡통 구할까",
      "content": "하버로 지급된 카루타 기간 날아가면 알몸인데 noKidnap('imageCollectDiv'); INVEN.Media.Resizer.collect('imageCollectDiv', '740'); // 신고하기 function report_bd() { var params = \"\"; params = \"rcidx=3&comeidx=5974&uid=6587663\"; INVEN.Links.reportArticle(params); } // 광고신고 INVEN.Links.spamArticle = function(params) { var repWin = window.open(\"https://www.inven.co.kr/common/report/spam/?\" + params,\"\",\"left=100,top=100,width=596,height=480,resizable=no,scrollbars=no,toolbar=0\"); } function report_spam() { var params = \"\"; params = \"type=board&index1=5974&index2=6587663\"; INVEN.Links.spamArticle(params); } // 스크랩 function scrapOpen() { var scrapWin = window.open('about:blank', 'scrap_add', 'left=50,top=50,height=50,width=50,scrollbars=no,resizable=no'); var fm = document.getElementById(\"fmAddToScrap\"); fm.target = \"scr"
    },
    {
      "title": "잠 안온다 ㅅㅂ",
      "content": "지금 자도 2시간도 못자게 생김그렇다고 밤새면 진짜 좆돰 noKidnap('imageCollectDiv'); INVEN.Media.Resizer.collect('imageCollectDiv', '740'); // 신고하기 function report_bd() { var params = \"\"; params = \"rcidx=3&comeidx=5974&uid=6587662\"; INVEN.Links.reportArticle(params); } // 광고신고 INVEN.Links.spamArticle = function(params) { var repWin = window.open(\"https://www.inven.co.kr/common/report/spam/?\" + params,\"\",\"left=100,top=100,width=596,height=480,resizable=no,scrollbars=no,toolbar=0\"); } function report_spam() { var params = \"\"; params = \"type=board&index1=5974&index2=6587662\"; INVEN.Links.spamArticle(params); } // 스크랩 function scrapOpen() { var scrapWin = window.open('about:blank', 'scrap_add', 'left=50,top=50,height=50,width=50,scrollbars=no,resizable=no'); var fm = document.getElementById(\"fmAddToScrap\"); fm.target"
    },
    {
      "title": "메갤에서 나로후닝님 관련 이상한 떡밥이도네요..",
      "content": "그냥 무시하면 될 듯함 noKidnap('imageCollectDiv'); INVEN.Media.Resizer.collect('imageCollectDiv', '740'); // 신고하기 function report_bd() { var params = \"\"; params = \"rcidx=3&comeidx=5974&uid=6587661\"; INVEN.Links.reportArticle(params); } // 광고신고 INVEN.Links.spamArticle = function(params) { var repWin = window.open(\"https://www.inven.co.kr/common/report/spam/?\" + params,\"\",\"left=100,top=100,width=596,height=480,resizable=no,scrollbars=no,toolbar=0\"); } function report_spam() { var params = \"\"; params = \"type=board&index1=5974&index2=6587661\"; INVEN.Links.spamArticle(params); } // 스크랩 function scrapOpen() { var scrapWin = window.open('about:blank', 'scrap_add', 'left=50,top=50,height=50,width=50,scrollbars=no,resizable=no'); var fm = document.getElementById(\"fmAddToScrap\"); fm.target = \"scrap_add\"; fm."
    },
    {
      "title": "진지하게 와헌도 이번 챌섭 추천리스트에 들만한듯",
      "content": "내가 볼땐 렌 상위호환느낌인거같은데 noKidnap('imageCollectDiv'); INVEN.Media.Resizer.collect('imageCollectDiv', '740'); // 신고하기 function report_bd() { var params = \"\"; params = \"rcidx=3&comeidx=5974&uid=6587660\"; INVEN.Links.reportArticle(params); } // 광고신고 INVEN.Links.spamArticle = function(params) { var repWin = window.open(\"https://www.inven.co.kr/common/report/spam/?\" + params,\"\",\"left=100,top=100,width=596,height=480,resizable=no,scrollbars=no,toolbar=0\"); } function report_spam() { var params = \"\"; params = \"type=board&index1=5974&index2=6587660\"; INVEN.Links.spamArticle(params); } // 스크랩 function scrapOpen() { var scrapWin = window.open('about:blank', 'scrap_add', 'left=50,top=50,height=50,width=50,scrollbars=no,resizable=no'); var fm = document.getElementById(\"fmAddToScrap\"); fm.target = \"scrap_ad"
    },
    {
      "title": "메이플 과자 그냥 네이버로 바로 질러버렸다",
      "content": "짱셔요는 그냥 편의점가서 사야지 noKidnap('imageCollectDiv'); INVEN.Media.Resizer.collect('imageCollectDiv', '740'); // 신고하기 function report_bd() { var params = \"\"; params = \"rcidx=3&comeidx=5974&uid=6587659\"; INVEN.Links.reportArticle(params); } // 광고신고 INVEN.Links.spamArticle = function(params) { var repWin = window.open(\"https://www.inven.co.kr/common/report/spam/?\" + params,\"\",\"left=100,top=100,width=596,height=480,resizable=no,scrollbars=no,toolbar=0\"); } function report_spam() { var params = \"\"; params = \"type=board&index1=5974&index2=6587659\"; INVEN.Links.spamArticle(params); } // 스크랩 function scrapOpen() { var scrapWin = window.open('about:blank', 'scrap_add', 'left=50,top=50,height=50,width=50,scrollbars=no,resizable=no'); var fm = document.getElementById(\"fmAddToScrap\"); fm.target = \"scrap_add\""
    },
    {
      "title": "ai 개커엽네 진짜",
      "content": "흐흐 noKidnap('imageCollectDiv'); INVEN.Media.Resizer.collect('imageCollectDiv', '740'); // 신고하기 function report_bd() { var params = \"\"; params = \"rcidx=3&comeidx=5974&uid=6587658\"; INVEN.Links.reportArticle(params); } // 광고신고 INVEN.Links.spamArticle = function(params) { var repWin = window.open(\"https://www.inven.co.kr/common/report/spam/?\" + params,\"\",\"left=100,top=100,width=596,height=480,resizable=no,scrollbars=no,toolbar=0\"); } function report_spam() { var params = \"\"; params = \"type=board&index1=5974&index2=6587658\"; INVEN.Links.spamArticle(params); } // 스크랩 function scrapOpen() { var scrapWin = window.open('about:blank', 'scrap_add', 'left=50,top=50,height=50,width=50,scrollbars=no,resizable=no'); var fm = document.getElementById(\"fmAddToScrap\"); fm.target = \"scrap_add\"; fm.submit(); "
    },
    {
      "title": "아 보스도 돌고 루시드도 해야하는데..",
      "content": "플래닛에 빠져버림ㅜ noKidnap('imageCollectDiv'); INVEN.Media.Resizer.collect('imageCollectDiv', '740'); // 신고하기 function report_bd() { var params = \"\"; params = \"rcidx=3&comeidx=5974&uid=6587657\"; INVEN.Links.reportArticle(params); } // 광고신고 INVEN.Links.spamArticle = function(params) { var repWin = window.open(\"https://www.inven.co.kr/common/report/spam/?\" + params,\"\",\"left=100,top=100,width=596,height=480,resizable=no,scrollbars=no,toolbar=0\"); } function report_spam() { var params = \"\"; params = \"type=board&index1=5974&index2=6587657\"; INVEN.Links.spamArticle(params); } // 스크랩 function scrapOpen() { var scrapWin = window.open('about:blank', 'scrap_add', 'left=50,top=50,height=50,width=50,scrollbars=no,resizable=no'); var fm = document.getElementById(\"fmAddToScrap\"); fm.target = \"scrap_add\"; fm.su"
    },
    {
      "title": "메이플 음식 콜라보 야무진걸로 계속하네",
      "content": "용사라면도 개인적으로 맛있었는데 롯데 과자도 맛있겠다 noKidnap('imageCollectDiv'); INVEN.Media.Resizer.collect('imageCollectDiv', '740'); // 신고하기 function report_bd() { var params = \"\"; params = \"rcidx=3&comeidx=5974&uid=6587655\"; INVEN.Links.reportArticle(params); } // 광고신고 INVEN.Links.spamArticle = function(params) { var repWin = window.open(\"https://www.inven.co.kr/common/report/spam/?\" + params,\"\",\"left=100,top=100,width=596,height=480,resizable=no,scrollbars=no,toolbar=0\"); } function report_spam() { var params = \"\"; params = \"type=board&index1=5974&index2=6587655\"; INVEN.Links.spamArticle(params); } // 스크랩 function scrapOpen() { var scrapWin = window.open('about:blank', 'scrap_add', 'left=50,top=50,height=50,width=50,scrollbars=no,resizable=no'); var fm = document.getElementById(\"fmAddToScrap\"); fm.target ="
    },
    {
      "title": "비온다…..",
      "content": "비오니깐 스읍국물 땡기네 하… noKidnap('imageCollectDiv'); INVEN.Media.Resizer.collect('imageCollectDiv', '740'); // 신고하기 function report_bd() { var params = \"\"; params = \"rcidx=3&comeidx=5974&uid=6587653\"; INVEN.Links.reportArticle(params); } // 광고신고 INVEN.Links.spamArticle = function(params) { var repWin = window.open(\"https://www.inven.co.kr/common/report/spam/?\" + params,\"\",\"left=100,top=100,width=596,height=480,resizable=no,scrollbars=no,toolbar=0\"); } function report_spam() { var params = \"\"; params = \"type=board&index1=5974&index2=6587653\"; INVEN.Links.spamArticle(params); } // 스크랩 function scrapOpen() { var scrapWin = window.open('about:blank', 'scrap_add', 'left=50,top=50,height=50,width=50,scrollbars=no,resizable=no'); var fm = document.getElementById(\"fmAddToScrap\"); fm.target = \"scrap_add\";"
    },
    {
      "title": "일러 3억주고 했는데",
      "content": "뭔가뭔ㄱ ㅏ맘에안듬왤케 뾰루퉁하지;; noKidnap('imageCollectDiv'); INVEN.Media.Resizer.collect('imageCollectDiv', '740'); // 신고하기 function report_bd() { var params = \"\"; params = \"rcidx=3&comeidx=5974&uid=6587652\"; INVEN.Links.reportArticle(params); } // 광고신고 INVEN.Links.spamArticle = function(params) { var repWin = window.open(\"https://www.inven.co.kr/common/report/spam/?\" + params,\"\",\"left=100,top=100,width=596,height=480,resizable=no,scrollbars=no,toolbar=0\"); } function report_spam() { var params = \"\"; params = \"type=board&index1=5974&index2=6587652\"; INVEN.Links.spamArticle(params); } // 스크랩 function scrapOpen() { var scrapWin = window.open('about:blank', 'scrap_add', 'left=50,top=50,height=50,width=50,scrollbars=no,resizable=no'); var fm = document.getElementById(\"fmAddToScrap\"); fm.target = \"scrap_a"
    },
    {
      "title": "편의점에 메이플과자들 들어왔네",
      "content": "근데 역 하나를 걸어가야되네 ㅅㅂ noKidnap('imageCollectDiv'); INVEN.Media.Resizer.collect('imageCollectDiv', '740'); // 신고하기 function report_bd() { var params = \"\"; params = \"rcidx=3&comeidx=5974&uid=6587651\"; INVEN.Links.reportArticle(params); } // 광고신고 INVEN.Links.spamArticle = function(params) { var repWin = window.open(\"https://www.inven.co.kr/common/report/spam/?\" + params,\"\",\"left=100,top=100,width=596,height=480,resizable=no,scrollbars=no,toolbar=0\"); } function report_spam() { var params = \"\"; params = \"type=board&index1=5974&index2=6587651\"; INVEN.Links.spamArticle(params); } // 스크랩 function scrapOpen() { var scrapWin = window.open('about:blank', 'scrap_add', 'left=50,top=50,height=50,width=50,scrollbars=no,resizable=no'); var fm = document.getElementById(\"fmAddToScrap\"); fm.target = \"scrap_add"
    },
    {
      "title": "보스 지금 나만 이상함?",
      "content": "뭐 보스 들어갈때마다 렉걸리고 패턴도 안나오고파탈도 ㅈㄴ 늦게되고 시퀀스 올려도 버프 다 안써지고 그러는디;;;서버 루나임 noKidnap('imageCollectDiv'); INVEN.Media.Resizer.collect('imageCollectDiv', '740'); // 신고하기 function report_bd() { var params = \"\"; params = \"rcidx=3&comeidx=5974&uid=6587650\"; INVEN.Links.reportArticle(params); } // 광고신고 INVEN.Links.spamArticle = function(params) { var repWin = window.open(\"https://www.inven.co.kr/common/report/spam/?\" + params,\"\",\"left=100,top=100,width=596,height=480,resizable=no,scrollbars=no,toolbar=0\"); } function report_spam() { var params = \"\"; params = \"type=board&index1=5974&index2=6587650\"; INVEN.Links.spamArticle(params); } // 스크랩 function scrapOpen() { var scrapWin = window.open('about:blank', 'scrap_add', 'left=50,top=50,height=50,width=50,scrollbars=no,resizable=no'); var fm = document.getE"
    }
  ],
  "analysis": {
    "todayIssue": "최근 메이플스토리에서는 다양한 클라이언트 업데이트가 이루어졌으며, 유저들 사이에서는 특정 캐릭터와 직업에 대한 사용 비율과 성능 논의가 활발히 이루어지고 있습니다.",
    "official": {
      "summary": "• 클라이언트 1.2.415 업데이트 발표\n• 클라이언트 1.2.414 업데이트 발표\n• 클라이언트 1.2.413 업데이트 발표",
      "date": "2026-05-14",
      "keywords": [
        "클라이언트 1.2.415",
        "클라이언트 1.2.414",
        "업데이트"
      ],
      "marketingTips": [
        "신규 클라이언트 업데이트 관련 홍보",
        "특정 캐릭터 성능 소개 이벤트 진행"
      ],
      "priceImpact": "이번 업데이트는 인기 캐릭터의 성능 변화가 예상되며, 이로 인해 관련 아이템의 시세에 영향을 줄 수 있습니다."
    },
    "dcinside": {
      "keywords": [
        {
          "word": "에반",
          "count": 5
        },
        {
          "word": "카데나",
          "count": 4
        },
        {
          "word": "제로",
          "count": 4
        },
        {
          "word": "칼리",
          "count": 3
        },
        {
          "word": "불독",
          "count": 3
        }
      ],
      "summary": "디시인사이드에서는 에반, 카데나와 같은 특정 캐릭터의 성능에 대한 논의가 활발하게 진행되고 있으며, 유저들 간의 직업 간의 상성을 비교하고 있습니다.",
      "marketingTips": [
        "유저 맞춤형 캐릭터 성능 개선 이벤트",
        "토론을 통한 유저 참여형 콘텐츠 마련"
      ],
      "priceImpact": "캐릭터 성능의 논의 덕분에 각 캐릭터 관련 아이템의 시세가 조정될 것으로 보입니다."
    },
    "inven": {
      "keywords": [
        {
          "word": "루시드",
          "count": 1
        },
        {
          "word": "버닝",
          "count": 1
        },
        {
          "word": "스킬",
          "count": 1
        },
        {
          "word": "미션",
          "count": 1
        },
        {
          "word": "보상",
          "count": 1
        }
      ],
      "summary": "인벤에서는 루시드 버닝 미션과 관련된 내용이 공유되며, 패치에 따라 미션 조건 및 보상이 변경될 것이라는 의견이 제기되고 있습니다.",
      "marketingTips": [
        "루시드 관련 이벤트 홍보",
        "루시드 패치로 인한 유저 리워드 제공"
      ],
      "priceImpact": "루시드 보상 및 패치 업데이트가 아이템 시세에 긍정적인 영향을 미칠 것으로 예측됩니다."
    },
    "seoSns": {
      "materials": [
        "루시드 버닝 미션이 추가되어 레벨업 기회를 놓치지 마세요!",
        "특정 캐릭터의 스킬 조정으로 새롭게 달라진 전투 경험을 느껴보세요.",
        "업데이트된 패치를 통해 주어진 보상을 확인하고 강력한 장비로 만들어보세요."
      ]
    },
    "youtubeAd": {
      "youtubers": []
    },
    "crm": [
      {
        "title": "(광고) 에반 성능 개선! 💎",
        "body": "(광고) 에반 관련 아이템, 시세가 오른다니 확인해보세요! 🚀"
      },
      {
        "title": "(광고) 루시드 미션 보상! 🔥",
        "body": "(광고) 루시드 보상으로 강력한 아이템 마련하세요! 💰"
      }
    ]
  }
}