{
  "lastUpdated": "2026-05-12T13:27:29.763Z",
  "officialPosts": [
    {
      "title": "클라이언트 1.2.414(3) 업데이트 안내",
      "date": "",
      "content": "",
      "link": "https://maplestory.nexon.com/news/update/803",
      "isRecent": false
    },
    {
      "title": "수정 클라이언트 1.2.414 업데이트 안내 (이벤트, 컨텐츠, 개선사항 및 오류 수정)",
      "date": "2026년 4월 17일",
      "content": "",
      "link": "https://maplestory.nexon.com/news/update/802",
      "isRecent": false
    },
    {
      "title": "수정 클라이언트 1.2.414 업데이트 안내 (공용 코어, 스킬 조정)",
      "date": "2026년 4월 20일",
      "content": "",
      "link": "https://maplestory.nexon.com/news/update/801",
      "isRecent": false
    },
    {
      "title": "클라이언트 1.2.413(4) 업데이트 안내",
      "date": "",
      "content": "",
      "link": "https://maplestory.nexon.com/news/update/800",
      "isRecent": false
    },
    {
      "title": "수정2 클라이언트 1.2.413 업데이트 안내 (컨텐츠, 개선사항 및 오류수정)",
      "date": "2026년 3월 23일",
      "content": "",
      "link": "https://maplestory.nexon.com/news/update/799",
      "isRecent": false
    }
  ],
  "dcPosts": [
    {
      "title": "내 게임 기록이 전시물로, '넥슨 뮤지엄' 제주도서 개관",
      "content": "🔼 넥슨뮤지엄 전시관 전경 (사진제공: 넥슨)[게임메카=신재연 기자] 넥슨은 12일, 넥슨뮤지엄이 4개월간의 리뉴얼을 마치고 개관했다고 밝혔다. 제주도에 위치한 넥슨뮤지엄은 아시아에서 처음으로 컴퓨터 박물관으로 개관했던 공간을 넥슨의 30년 역사를 현대적인 매체로 재해석한 국내 유일의 게임 브랜드 거점으로 탈바꿈시킨 공간이다. 이번 리뉴얼은 기존 기술 중심의 전시 방식에서 벗어나, 게임을 즐기는 주체를 '플레이어'로 정의하고 이들의 경험에 초점을 맞춘 것이 특징이다.새롭게 단장한 넥슨뮤지엄은 대한민국과 넥슨이 선도해 온 온라인 게임의 역사를 조명한다. 이에 맞춰 관람객의 플레이 기록을 오프라인 공간으로 옮겨, 가상 세계를 직접 체험하는 기회를 선사한다. 현장에서는 올해 서비스 30주년을 맞이하는 바람의나라를 비롯해 카트라이더, 메이플스토리, 마비노기, 던전앤파이터 등 세대를 아우르는 넥슨의 다양한 IP를 한자리에서 만날 수 있다.넥슨뮤지엄을 방문한 관람객은 넥슨 계정으로 로그인해 여러 게임에 흩어져 있던 자신의 플레이 기록을 한곳에 모아 '나만의 맞춤형 관람'을 경험할 수 있다. 매칭된 IP는 전시의 시작부터 끝까지 관람 여정에 동행하며, 넥슨 계정이 없거나 연동하지 않은 관람객에게는 무작위 IP가 배정되어 넥슨 게임들을 새롭게 접하는 기회를 제공한다.🔼 넥슨뮤지엄 이미지 (사진제공: 넥슨뮤지엄)이번 넥슨뮤지엄 개관을 기념하는 두 개의 상설 전시도 만날 수 있다. 이번 상설 전시들은 1층부터 3층까지 전관에 걸쳐 진행된다. 1층과 2층에서는 '플레이어들: 죽지마! 계속해!' 전시가, 3층에서는 '안녕, 나"
    },
    {
      "title": "★ 메이플 뉴비 가이드 / 직업공략/ 자주 하는 질문 ★",
      "content": "뉴비가이드(파란색 글씨 클릭시 이동)뉴비 복귀유저 메알못 모두를 위한 뉴비가이드! 메이플에대해 모르는게 있다면 무조건 필독추옵 스타포스 잠재 사냥터 등등등 모르는게 있다고요? 뉴비가이드 보세요갤길 리스트도 있습니다V매트릭스 (5차전직) 가이드(파란색 글씨 클릭시 이동)기존 시스템과 너무다른 5차 전직!가장쉽게 풀이해주는 가이드유효코어, 강화하는법, 슬롯강화, 직업별 코어젬 소모 갯수 등을 알려드립니다메이플 유니온, 링크 가이드(파란색 글씨 클릭시 이동)기존 캐릭터 카드시스템과 아르바이트를 합친 메이플 유니온그리고 링크스킬추천 유니온/ 링크 캐릭터와 양성법을 알려드려요메이플스토리 직업별 가이드(파란색 글씨 클릭시 이동)메이플스토리 갤러리 유저들이 쓴 실전형 직업별 가이드코어강화. 보스별 공략, 템세팅까지 한번에메이플스토리 정보(파란색 글씨 클릭시 이동)각종 표와 자주묻는 질문들을 전부모은 목록상위보스공략, 주흔작 판별법, 스타포스, 시세검색등을 알려드려요메이플스토리 컨텐츠(파란색 글씨 클릭시 이동)정말 다양한 메이플의 컨텐츠들!시드, 월파, 싸전귀 등등"
    },
    {
      "title": "나늖짱<< 욕 처먹기 시작하니까 바로 빤스런",
      "content": "전형적인 infp 회피형몇 시간 뒤쯤 와서 또 쿨찐 초식 껑껑 거릴 듯- dc official App"
    },
    {
      "title": "크로아에서 게임 시작해도 ㄱㅊ음?",
      "content": "서버는 크로아 길드는 Alpha"
    },
    {
      "title": "우리형<<< 익칼 첫 도전하기전엔 동층딜 어쩌고저쩌고",
      "content": "말은 시발 청산유수마냥 입 존나 털어댔음근데 막상 도전해보니 개쳐맞고 뒤지고 싸대기 쳐맞고 계속날라가더니어느순간부터 소심해져서 게이마냥 동층딜 포기함"
    },
    {
      "title": "두바이 방송키기전에 익칼 항다닥 잡는거엿내,,",
      "content": "ㅋㅋ"
    },
    {
      "title": "근데 나늖짱 순수하게 웃기지않나 ㄹㅇ 아닌가 하 ㄹ",
      "content": "약간 마음의소리 같은 재미가 잇는데 ㄹㅇ"
    },
    {
      "title": "이쿠 < 전성기 기준 지금 환산 5등권은 가능함?",
      "content": "시대 보정해도 올 22성 따리론 힘듬?"
    },
    {
      "title": "생마석은 뒤지게 안 붙는데 파괴5%는 왤케 잘 터짐?",
      "content": "이딴게 게임임?"
    },
    {
      "title": "박근혜는성인이성인물보는게뭐가문제냐고",
      "content": "했었는데문재앙찢재명이새끼들은ㄹㅇ자돕자안하나...딸딸이까지통제시키노"
    },
    {
      "title": "피로하다 피로해",
      "content": "어흑"
    },
    {
      "title": "우리형 진짜 메이플에 진심이네ㅋㅋ",
      "content": "카데나까지 키우면 3캐릭 키우는건데 ㄷㄷㄷㄷㄷ"
    },
    {
      "title": "은호햄이 제논해야 꿀잼각 나오는데 ㄲㅂ....",
      "content": "우리형 제논도 2등 가야하는데..."
    },
    {
      "title": "사요쯔구 나늖짱 갑신",
      "content": "딱 비슷한 장애인들- dc official App"
    },
    {
      "title": "너무불행해",
      "content": "멘헤라왔어"
    },
    {
      "title": "나늖짱< 얘는 지가 웃기다고 생각함..?",
      "content": "진지하게 장애인 같은데 자아 존나 비대한 느낌like 사요쯔구- dc official App"
    }
  ],
  "invenPosts": [
    {
      "title": "(추가4) 테섭 신규이벤트&라이브&캐시 요약: 쇼케이스 일정 & 진 보스 등 : 메이플  오버드라이브 쇼케이스 날짜",
      "content": "[수정/추가 사항]1. 진 소울 관련 사항 추가※ 위대한 메이플 용사 진의 소울 선택권 사용 시 아래의 소울 중 하나를 선택하여 획득할 수 있습니다. - 위대한 메이플 용사 진의 소울 (공격력 3%) - 위대한 메이플 용사 진의 소울 (마력 3%)2. 진 보스 이벤트 부분 좀 더 보시기 편하도록 재배치하고 솔 에르다와 조각 교불인 점 추가했습니다 3. 쇼케이스 페이지 링크(https://maplestory.nexon.com/promotion/event/2026/20260507/event01) 등 일부 내용 보충했습니다4. 추가로 진행되는 오프라인 이벤트, 콜라보 음식과 굿즈 등 관련 페이지 오픈되어 링크 추가했습니다 : https://mapleisland.nexon.com/mapleattack-----------------안녕하세요이 글은 오늘 진행된 테섭과 라이브의 핵심이 되는 내용들을 간략히 보실 수 있게 정리한 것입니다이후 여력 되는 대로 보충하겠습니다 수정된 내용은 글 맨 위에서 말씀 드립니다 누락된 혹은 잘못 적은 부분은 말씀해 주시면 감사히 수정하겠습니다 -------------------- [들어가기 전에 지금 체크할만한 사항]1. <진의 신비한 정원> 이벤트가 종료를 앞두고 있으므로(~5/13) 종료 전 코인샵 이용, 누적 보상 수령 필요합니다2. <진의 신비한 정원> 히든 미션 수행 : 누적 굴린 주사위 개수 90개 이상 달성 후 1) 마가티아 제뉴미스트 연구소 202호의 미완성 마법진과 호문스큘러 라이딩에 탑승한 채로 대화 : 독! 이펙트2) 이벤트 맵의 진에게 \"안녕\" 인사 후 정답으로 \""
    },
    {
      "title": "지금 밖에 있는 사람있나??",
      "content": "17도인데 지금 날씨에 반팔 입으면 추웡? noKidnap('imageCollectDiv'); INVEN.Media.Resizer.collect('imageCollectDiv', '740'); // 신고하기 function report_bd() { var params = \"\"; params = \"rcidx=3&comeidx=5974&uid=6565505\"; INVEN.Links.reportArticle(params); } // 광고신고 INVEN.Links.spamArticle = function(params) { var repWin = window.open(\"https://www.inven.co.kr/common/report/spam/?\" + params,\"\",\"left=100,top=100,width=596,height=480,resizable=no,scrollbars=no,toolbar=0\"); } function report_spam() { var params = \"\"; params = \"type=board&index1=5974&index2=6565505\"; INVEN.Links.spamArticle(params); } // 스크랩 function scrapOpen() { var scrapWin = window.open('about:blank', 'scrap_add', 'left=50,top=50,height=50,width=50,scrollbars=no,resizable=no'); var fm = document.getElementById(\"fmAddToScrap\"); fm.target = \"scra"
    },
    {
      "title": "어떤 사람이 더 짜증나나요",
      "content": "ㄷㄷ noKidnap('imageCollectDiv'); INVEN.Media.Resizer.collect('imageCollectDiv', '740'); const _IPOLL_RESULT_ = {\"423234\":{\"type\":\"vote\",\"setting\":{\"idx\":423234,\"state\":\"Y\",\"poll_type\":1,\"title\":\"왜저래 인간\",\"image\":\"\",\"explain\":\"\",\"random\":\"N\",\"multi_select\":\"N\",\"multi_limit\":0,\"anonymity\":\"N\",\"thumb_order\":\"right\",\"end_set\":\"date\",\"end_date\":\"2026-05-13 22:25:59\",\"end_count_limit\":0,\"result_view\":\"poll\",\"memnick\":\"가을소설\",\"participant\":1,\"other\":\"\",\"gamerank\":\"N\",\"come_idx\":5974,\"uidx\":6565504,\"use_html\":\"N\",\"link\":\"https://www.inven.co.kr/board/maple/5974/6565504\"},\"choice\":[],\"answers\":[{\"idx\":1354701,\"sidx\":423234,\"order\":1,\"answer\":\"스포충\",\"thumbnail\":\"\",\"ori_image\":\"\"},{\"idx\":1354702,\"sidx\":423234,\"order\":2,\"answer\":\"남탓충\",\"thumbnail\":\"\",\"ori_image\":\"\"},{\"idx\":1354703,\"sidx\":423234,\"order\":3,\""
    },
    {
      "title": "창섭이가 밸패 못하는편임?",
      "content": "그럼 제일 잘햇을때가 언제임 noKidnap('imageCollectDiv'); INVEN.Media.Resizer.collect('imageCollectDiv', '740'); // 신고하기 function report_bd() { var params = \"\"; params = \"rcidx=3&comeidx=5974&uid=6565503\"; INVEN.Links.reportArticle(params); } // 광고신고 INVEN.Links.spamArticle = function(params) { var repWin = window.open(\"https://www.inven.co.kr/common/report/spam/?\" + params,\"\",\"left=100,top=100,width=596,height=480,resizable=no,scrollbars=no,toolbar=0\"); } function report_spam() { var params = \"\"; params = \"type=board&index1=5974&index2=6565503\"; INVEN.Links.spamArticle(params); } // 스크랩 function scrapOpen() { var scrapWin = window.open('about:blank', 'scrap_add', 'left=50,top=50,height=50,width=50,scrollbars=no,resizable=no'); var fm = document.getElementById(\"fmAddToScrap\"); fm.target = \"scrap_add\"; "
    },
    {
      "title": "나도 언젠가 데티해방 할날이 오겠지",
      "content": "내가 올라갈 깜냥은 안되니까세상이 나한테까지 내려올 날을 기다린다 noKidnap('imageCollectDiv'); INVEN.Media.Resizer.collect('imageCollectDiv', '740'); // 신고하기 function report_bd() { var params = \"\"; params = \"rcidx=3&comeidx=5974&uid=6565502\"; INVEN.Links.reportArticle(params); } // 광고신고 INVEN.Links.spamArticle = function(params) { var repWin = window.open(\"https://www.inven.co.kr/common/report/spam/?\" + params,\"\",\"left=100,top=100,width=596,height=480,resizable=no,scrollbars=no,toolbar=0\"); } function report_spam() { var params = \"\"; params = \"type=board&index1=5974&index2=6565502\"; INVEN.Links.spamArticle(params); } // 스크랩 function scrapOpen() { var scrapWin = window.open('about:blank', 'scrap_add', 'left=50,top=50,height=50,width=50,scrollbars=no,resizable=no'); var fm = document.getElementById(\"fmAddToScrap\"); fm.t"
    },
    {
      "title": "강원기였으면 나 이제야 노말림보 파티격 갈때 됐겠지?",
      "content": "창섭이가 확실히 템포가 빨라 noKidnap('imageCollectDiv'); INVEN.Media.Resizer.collect('imageCollectDiv', '740'); // 신고하기 function report_bd() { var params = \"\"; params = \"rcidx=3&comeidx=5974&uid=6565501\"; INVEN.Links.reportArticle(params); } // 광고신고 INVEN.Links.spamArticle = function(params) { var repWin = window.open(\"https://www.inven.co.kr/common/report/spam/?\" + params,\"\",\"left=100,top=100,width=596,height=480,resizable=no,scrollbars=no,toolbar=0\"); } function report_spam() { var params = \"\"; params = \"type=board&index1=5974&index2=6565501\"; INVEN.Links.spamArticle(params); } // 스크랩 function scrapOpen() { var scrapWin = window.open('about:blank', 'scrap_add', 'left=50,top=50,height=50,width=50,scrollbars=no,resizable=no'); var fm = document.getElementById(\"fmAddToScrap\"); fm.target = \"scrap_add\"; "
    },
    {
      "title": "어센트9렙 vs 야누스20렙",
      "content": "현상황요번주 목요일 레벨280지금어센트1렙 야누스10렙투력 9500해방진행중인데잡을 수 있는보스 하루시까지하드윌이랑 가엔슬 연습중인디이건 곧 클리어 가능할 것 같은데하루 3-4소재 사냥이상황에서어센트9렙 찍으면진듄더나 다른 검밑솔보스할 때 도움 많이 되나요??그렇게 유의미하지 않으면야누스20렙이나 올려서 더 편하게사냥하는게 나을까요?? noKidnap('imageCollectDiv'); INVEN.Media.Resizer.collect('imageCollectDiv', '740'); // 신고하기 function report_bd() { var params = \"\"; params = \"rcidx=3&comeidx=5974&uid=6565500\"; INVEN.Links.reportArticle(params); } // 광고신고 INVEN.Links.spamArticle = function(params) { var repWin = window.open(\"https://www.inven.co.kr/common/report/spam/?\" + params,\"\",\"left=100,top=100,width=596,height=480,resizable=no,scrollbars=no,toolbar=0\"); } function report_spam() { var params = \"\"; params = \"type=board&index1=5974&index2=6565500\"; INVEN.Links.spamArticle(params); } // 스크랩 function scrapOpen() { var scrapWin = window."
    },
    {
      "title": "익스우 1, 2페에서 피가 애매하게 남으면 어떡하지",
      "content": "5~6퍼 이렇게 남아서 둘 다 준극으로 넘기긴 했는데이러면 결국 최소컷할 때 오리진 한 번 못 쓰긴 해어차피 극딜 썼어도 딜 날리는 거니까 비슷하려나? 모르겠네 noKidnap('imageCollectDiv'); INVEN.Media.Resizer.collect('imageCollectDiv', '740'); // 신고하기 function report_bd() { var params = \"\"; params = \"rcidx=3&comeidx=5974&uid=6565499\"; INVEN.Links.reportArticle(params); } // 광고신고 INVEN.Links.spamArticle = function(params) { var repWin = window.open(\"https://www.inven.co.kr/common/report/spam/?\" + params,\"\",\"left=100,top=100,width=596,height=480,resizable=no,scrollbars=no,toolbar=0\"); } function report_spam() { var params = \"\"; params = \"type=board&index1=5974&index2=6565499\"; INVEN.Links.spamArticle(params); } // 스크랩 function scrapOpen() { var scrapWin = window.open('about:blank', 'scrap_add', 'left=50,top=50,height=50,width=50,scrollbars=no,resizable=no'); v"
    },
    {
      "title": "다조값이 떨어질 이유가 뭐 있지",
      "content": "다조 팔아다가 유챔 템 살 때도 아니고 미라클 막 지났고 샤타는 다담주가 정배고메소 땡길 타이밍이 아닌걸로 보이는데끽해야 유입들 접으면서 파는건데 유입들이 캐서 들고 있는것보다 버는 족적 쓸건데 ㄹㅇ 모르겠음 noKidnap('imageCollectDiv'); INVEN.Media.Resizer.collect('imageCollectDiv', '740'); // 신고하기 function report_bd() { var params = \"\"; params = \"rcidx=3&comeidx=5974&uid=6565498\"; INVEN.Links.reportArticle(params); } // 광고신고 INVEN.Links.spamArticle = function(params) { var repWin = window.open(\"https://www.inven.co.kr/common/report/spam/?\" + params,\"\",\"left=100,top=100,width=596,height=480,resizable=no,scrollbars=no,toolbar=0\"); } function report_spam() { var params = \"\"; params = \"type=board&index1=5974&index2=6565498\"; INVEN.Links.spamArticle(params); } // 스크랩 function scrapOpen() { var scrapWin = window.open('about:blank', 'scrap_add', 'left=50,top=50,height=50,width=50,scro"
    },
    {
      "title": "밸런스의 핵심은 꾹,딸깍이 쏀게 문제인거지",
      "content": "상위권에 포진한 카데나,블래,제로,에반,메르,칼리,아크 << 이런직업들은 보스배율 낮게 깎여도 태클 잘 안걸리는데가장 최근에 유저가 측정했던 체급지표인 진캐챌 참고해보면제논은 특수스탯쓴다고 제로 블래 아크랑 비비면서 5위권안에서 놀고있고보마는 그냥 아무이유도 없이 꾹딸깍이 체급으로 에반메르랑 비비면서 동꼽으로 보스따고 앉아있고진짜 미친 최하위권 직업 몇몇 아니면 지금 밸런스 떡밥의 핵심은 난이도 비례 딜량이 지나치게 높은 놈들이 밸런스 패치의 기준 자체를 모호하게 만든단 거임걍 보마랑 제논 칼질 하기 전엔 다른직업 조정 아무리 해봤자인듯 noKidnap('imageCollectDiv'); INVEN.Media.Resizer.collect('imageCollectDiv', '740'); // 신고하기 function report_bd() { var params = \"\"; params = \"rcidx=3&comeidx=5974&uid=6565497\"; INVEN.Links.reportArticle(params); } // 광고신고 INVEN.Links.spamArticle = function(params) { var repWin = window.open(\"https://www.inven.co.kr/common/report/spam/?\" + params,\"\",\"left=100,top=100,width=596,height=480,resizable=no,scrollbars=no,toolbar=0\"); } function report_spam() { var params = \"\"; params = \"type=board&i"
    },
    {
      "title": "캐릭터 AI 그림 받으실분",
      "content": "재획하면서 돌리게캐릭터 코디가 수수하거나 너무 단순하면 퀄리티가 낮게 나오더라장식 많거나 화려한 게 잘 나오고 원하는 자세나 장면 정해주면 좋음10명 정도까진 괜찮을 듯 그림 다시 뽑느라 시간 좀 걸릴 수도 있음 noKidnap('imageCollectDiv'); INVEN.Media.Resizer.collect('imageCollectDiv', '740'); // 신고하기 function report_bd() { var params = \"\"; params = \"rcidx=3&comeidx=5974&uid=6565496\"; INVEN.Links.reportArticle(params); } // 광고신고 INVEN.Links.spamArticle = function(params) { var repWin = window.open(\"https://www.inven.co.kr/common/report/spam/?\" + params,\"\",\"left=100,top=100,width=596,height=480,resizable=no,scrollbars=no,toolbar=0\"); } function report_spam() { var params = \"\"; params = \"type=board&index1=5974&index2=6565496\"; INVEN.Links.spamArticle(params); } // 스크랩 function scrapOpen() { var scrapWin = window.open('about:blank', 'scrap_add', 'left=50,top=50,height=50,width=50,sc"
    },
    {
      "title": "엘보만 떳다하면 다들 어센트 갈겨버리니까",
      "content": "엘보 못 먹는 사람이 종종 나오네 noKidnap('imageCollectDiv'); INVEN.Media.Resizer.collect('imageCollectDiv', '740'); // 신고하기 function report_bd() { var params = \"\"; params = \"rcidx=3&comeidx=5974&uid=6565495\"; INVEN.Links.reportArticle(params); } // 광고신고 INVEN.Links.spamArticle = function(params) { var repWin = window.open(\"https://www.inven.co.kr/common/report/spam/?\" + params,\"\",\"left=100,top=100,width=596,height=480,resizable=no,scrollbars=no,toolbar=0\"); } function report_spam() { var params = \"\"; params = \"type=board&index1=5974&index2=6565495\"; INVEN.Links.spamArticle(params); } // 스크랩 function scrapOpen() { var scrapWin = window.open('about:blank', 'scrap_add', 'left=50,top=50,height=50,width=50,scrollbars=no,resizable=no'); var fm = document.getElementById(\"fmAddToScrap\"); fm.target = \"scrap_add"
    },
    {
      "title": "카르시온부터 경험치 뒤지게 안 오르는 구마잉",
      "content": "카르시온 재획용 부캐 2소재 재획비 하나만 빨고 했더니 한 0.14퍼? 오른듯1소재인지 2소재인지 다른 캐릭 다녀와서 한거라 헷갈리넴 noKidnap('imageCollectDiv'); INVEN.Media.Resizer.collect('imageCollectDiv', '740'); // 신고하기 function report_bd() { var params = \"\"; params = \"rcidx=3&comeidx=5974&uid=6565494\"; INVEN.Links.reportArticle(params); } // 광고신고 INVEN.Links.spamArticle = function(params) { var repWin = window.open(\"https://www.inven.co.kr/common/report/spam/?\" + params,\"\",\"left=100,top=100,width=596,height=480,resizable=no,scrollbars=no,toolbar=0\"); } function report_spam() { var params = \"\"; params = \"type=board&index1=5974&index2=6565494\"; INVEN.Links.spamArticle(params); } // 스크랩 function scrapOpen() { var scrapWin = window.open('about:blank', 'scrap_add', 'left=50,top=50,height=50,width=50,scrollbars=no,resizable=no'); var fm = documen"
    },
    {
      "title": "쌍레 에테뚝사기 VS 윗잠만사서 에디직작",
      "content": "아까도 올렸는데 후자 에디는 쿨감1초 + 유효옵 아무거나 정도로타협할생각인데 둘중 하나고르면 님들 뭐하심?18성쓰다가 일단 21까진 누를거임 noKidnap('imageCollectDiv'); INVEN.Media.Resizer.collect('imageCollectDiv', '740'); // 신고하기 function report_bd() { var params = \"\"; params = \"rcidx=3&comeidx=5974&uid=6565493\"; INVEN.Links.reportArticle(params); } // 광고신고 INVEN.Links.spamArticle = function(params) { var repWin = window.open(\"https://www.inven.co.kr/common/report/spam/?\" + params,\"\",\"left=100,top=100,width=596,height=480,resizable=no,scrollbars=no,toolbar=0\"); } function report_spam() { var params = \"\"; params = \"type=board&index1=5974&index2=6565493\"; INVEN.Links.spamArticle(params); } // 스크랩 function scrapOpen() { var scrapWin = window.open('about:blank', 'scrap_add', 'left=50,top=50,height=50,width=50,scrollbars=no,resizable=no'); var fm = doc"
    },
    {
      "title": "요즘 11만대가 8천명넘어선지 공팟도 하발팟 꽤보이더라",
      "content": "원래 익적 익칼팟도 보일까말까였다가 요샌 공팟에서도 보이는거보면 인겜평균이 1년동안 1만정도 올라온듯함 ㄹㅇ...데티해방한 지인분들도 요즘 10추에 올라오는거보면 데티해방도 슬슬 도전할날이 다가오는게 느껴짐 noKidnap('imageCollectDiv'); INVEN.Media.Resizer.collect('imageCollectDiv', '740'); // 신고하기 function report_bd() { var params = \"\"; params = \"rcidx=3&comeidx=5974&uid=6565492\"; INVEN.Links.reportArticle(params); } // 광고신고 INVEN.Links.spamArticle = function(params) { var repWin = window.open(\"https://www.inven.co.kr/common/report/spam/?\" + params,\"\",\"left=100,top=100,width=596,height=480,resizable=no,scrollbars=no,toolbar=0\"); } function report_spam() { var params = \"\"; params = \"type=board&index1=5974&index2=6565492\"; INVEN.Links.spamArticle(params); } // 스크랩 function scrapOpen() { var scrapWin = window.open('about:blank', 'scrap_add', 'left=50,top=50,height=50,width=50,scrol"
    },
    {
      "title": "코디 프리셋 모루 아이템 정상화 기원 439일차",
      "content": "코디 프리셋 모루 아이템 정상화 기원 439일차22년 7월 28일 코디 프리셋 신규 추가.단, 전투복 탭이 따로 없어서 전투복 효과 미적용24년 1월 18일전투복 탭이 따로 생겨서 전투복 효과 적용 가능25년 4월 17일코디창, 뷰티룸 등 데코레이션 인벤토리라는 개별 UI로 독립그러나, 코디 프리셋이 추가된지 오랜 기간이 지났지만아직까지도 전투복 효과를 적용하면서 신비의 모루를 활용한 일반 아이템 외형 코디를 하는 것은 불가능합니다.추가적으로 엔젤릭버스터는 모루 코디로 생활하기가 불가능합니다.일반 장비 아이템들은 모두 티어 모드에 장착하게 되는데, 드레스 업으로 변신할 경우소울슈터와 소울링을 제외하고는 모두 안 보이게 되므로 엔젤릭버스터 모드에는 신비의 모루를 이용한 코디로 생활하기가 불가능 합니다.해당 부분의 개선이 필요합니다. noKidnap('imageCollectDiv'); INVEN.Media.Resizer.collect('imageCollectDiv', '740'); // 신고하기 function report_bd() { var params = \"\"; params = \"rcidx=3&comeidx=5974&uid=6565491\"; INVEN.Links.reportArticle(params); } // 광고신고 INVEN.Links.spamArticle = function(params) { var repWin = window.open(\"https://www.inven.co.kr/common/report/spam/?\" + params,\"\",\"left=100,top=100,width=596,height="
    },
    {
      "title": "10추글 저능아랑은 왜 대화 하고 있는거야?",
      "content": "누르면 소리나는 인형같은건가? noKidnap('imageCollectDiv'); INVEN.Media.Resizer.collect('imageCollectDiv', '740'); // 신고하기 function report_bd() { var params = \"\"; params = \"rcidx=3&comeidx=5974&uid=6565490\"; INVEN.Links.reportArticle(params); } // 광고신고 INVEN.Links.spamArticle = function(params) { var repWin = window.open(\"https://www.inven.co.kr/common/report/spam/?\" + params,\"\",\"left=100,top=100,width=596,height=480,resizable=no,scrollbars=no,toolbar=0\"); } function report_spam() { var params = \"\"; params = \"type=board&index1=5974&index2=6565490\"; INVEN.Links.spamArticle(params); } // 스크랩 function scrapOpen() { var scrapWin = window.open('about:blank', 'scrap_add', 'left=50,top=50,height=50,width=50,scrollbars=no,resizable=no'); var fm = document.getElementById(\"fmAddToScrap\"); fm.target = \"scrap_add\";"
    },
    {
      "title": "가끔 채널이동 엔터 눌러도 왜 안바뀌나했는데",
      "content": "펫버프 걸릴떄 채널이동버튼 누르면 안되는거였녜몇년전에 신해조 펫버프걸릴떄 리턴주문서 안걸린적있는거로아는데 아직도 안고쳣네 noKidnap('imageCollectDiv'); INVEN.Media.Resizer.collect('imageCollectDiv', '740'); // 신고하기 function report_bd() { var params = \"\"; params = \"rcidx=3&comeidx=5974&uid=6565489\"; INVEN.Links.reportArticle(params); } // 광고신고 INVEN.Links.spamArticle = function(params) { var repWin = window.open(\"https://www.inven.co.kr/common/report/spam/?\" + params,\"\",\"left=100,top=100,width=596,height=480,resizable=no,scrollbars=no,toolbar=0\"); } function report_spam() { var params = \"\"; params = \"type=board&index1=5974&index2=6565489\"; INVEN.Links.spamArticle(params); } // 스크랩 function scrapOpen() { var scrapWin = window.open('about:blank', 'scrap_add', 'left=50,top=50,height=50,width=50,scrollbars=no,resizable=no'); var fm = document.getEl"
    },
    {
      "title": "썬콜은 언제부터쌨음?",
      "content": "적당히 쌔고쉬운라인 정도로 인식하고있었는데 여론보니까 그거보다 더 높은거같은데 noKidnap('imageCollectDiv'); INVEN.Media.Resizer.collect('imageCollectDiv', '740'); // 신고하기 function report_bd() { var params = \"\"; params = \"rcidx=3&comeidx=5974&uid=6565488\"; INVEN.Links.reportArticle(params); } // 광고신고 INVEN.Links.spamArticle = function(params) { var repWin = window.open(\"https://www.inven.co.kr/common/report/spam/?\" + params,\"\",\"left=100,top=100,width=596,height=480,resizable=no,scrollbars=no,toolbar=0\"); } function report_spam() { var params = \"\"; params = \"type=board&index1=5974&index2=6565488\"; INVEN.Links.spamArticle(params); } // 스크랩 function scrapOpen() { var scrapWin = window.open('about:blank', 'scrap_add', 'left=50,top=50,height=50,width=50,scrollbars=no,resizable=no'); var fm = document.getElementById(\"fmAddToScrap\""
    },
    {
      "title": "님들 여태 카톡 선물 몇개 받음?",
      "content": "나 1400개 받음 noKidnap('imageCollectDiv'); INVEN.Media.Resizer.collect('imageCollectDiv', '740'); // 신고하기 function report_bd() { var params = \"\"; params = \"rcidx=3&comeidx=5974&uid=6565487\"; INVEN.Links.reportArticle(params); } // 광고신고 INVEN.Links.spamArticle = function(params) { var repWin = window.open(\"https://www.inven.co.kr/common/report/spam/?\" + params,\"\",\"left=100,top=100,width=596,height=480,resizable=no,scrollbars=no,toolbar=0\"); } function report_spam() { var params = \"\"; params = \"type=board&index1=5974&index2=6565487\"; INVEN.Links.spamArticle(params); } // 스크랩 function scrapOpen() { var scrapWin = window.open('about:blank', 'scrap_add', 'left=50,top=50,height=50,width=50,scrollbars=no,resizable=no'); var fm = document.getElementById(\"fmAddToScrap\"); fm.target = \"scrap_add\"; fm.su"
    }
  ],
  "analysis": {
    "todayIssue": "최근 메이플스토리의 클라이언트 업데이트가 잇달아 발표되어 커뮤니티에서 큰 관심을 받고 있습니다.",
    "official": {
      "summary": "• 클라이언트 1.2.414 업데이트 공지\n• 이벤트, 콘텐츠 개선 및 오류 수정\n• 스킬 조정 및 공용 코어 변경\n• 과거 클라이언트 업데이트 재공지",
      "date": "2026년 4월 17일",
      "keywords": [
        "클라이언트 1.2.414",
        "이벤트",
        "오류 수정",
        "스킬 조정",
        "공용 코어"
      ],
      "marketingTips": [
        "이벤트 관련 아이템을 강조하여 사용자 참여 유도",
        "신규 콘텐츠 및 개선 사항을 활용한 광고 캠페인 진행"
      ],
      "priceImpact": "방대한 업데이트로 인해 일부 아이템 수요가 증가할 가능성이 있으며, 관련 아이템의 시세에 긍정적인 영향을 미칠 수 있습니다."
    },
    "dcinside": {
      "keywords": [
        {
          "word": "서버",
          "count": 1
        },
        {
          "word": "익칼",
          "count": 2
        },
        {
          "word": "직업",
          "count": 1
        },
        {
          "word": "카데나",
          "count": 1
        },
        {
          "word": "밸런스",
          "count": 1
        }
      ],
      "summary": "디시인사이드 커뮤니티에서 메이플스토리의 직업 밸런스와 관련된 의견이 활발히 오가고 있으며, 익칼과 관련된 도전과제에 대한 언급이 많습니다.",
      "marketingTips": [
        "특정 직업에 맞춘 장비 세트 할인 이벤트",
        "익칼 도전과제로 사용자 응대 게시판에서 참여 유도"
      ],
      "priceImpact": "익칼 관련 아이템과 카데나의 시세가 최근 도전 인구 증가에 따라 상승할 여지가 있습니다."
    },
    "inven": {
      "keywords": [
        {
          "word": "어센트",
          "count": 2
        },
        {
          "word": "엘보",
          "count": 1
        },
        {
          "word": "시세",
          "count": 1
        },
        {
          "word": "아이템",
          "count": 1
        },
        {
          "word": "진 캐릭터",
          "count": 1
        }
      ],
      "summary": "인벤에서는 어센트와 엘보의 밸런스 및 관련 시세에 대한 토론이 이루어지고 있으며, 플레이어들이 직접 경험한 문제들이 공유되고 있습니다.",
      "marketingTips": [
        "어센트 관련 아이템 세일 프로모션",
        "엘보 및 진 캐릭터의 거래 관련 정보를 활용한 정보 캠페인"
      ],
      "priceImpact": "어센트와 엘보의 거래 시세가 유저들의 경험담에 따라 변동성이 커질 것으로 예상됩니다."
    },
    "seo": [
      "메이플 인기 직업 관련 정보",
      "한정 아이템 시세 변동 예측",
      "최신 패치 정보를 실시간으로",
      "밸런스 패치 요약",
      "커뮤니티 인기 게시글 모음"
    ],
    "youtube": [
      "메이플 신규 패치 해설 영상",
      "익칼 도전기 일상 브이로그",
      "어센트 전투 팁 영상",
      "직업별 최적 세팅 방법 소개"
    ],
    "push": [
      {
        "title": "(광고) 메이플 신규 패치로 아이템 시세 올라가!",
        "content": "(광고) 지금 메이플스토리 시세를 확인해 보세요!📈"
      },
      {
        "title": "(광고) 메이플 익칼 도전, 장비 준비 완료?",
        "content": "(광고) 내 장비가 필요해요! 시세 확인하고 거래 시작하세요!🛒"
      }
    ]
  }
}